{
  "id": "PAC-2026-018",
  "idade": 52,
  "gestante": false,
  "deficiencia": false,
  "hora_entrada": "17:00",
  "leituras": [
    {
      "hora": "17:00",
      "consciente": true,
      "glasgow": 15,
      "spo2": 95,
      "frequencia_cardiaca": 92,
      "temperatura": 37.3,
      "escala_dor": 4,
      "vomitos_por_hora": 1,
      "pulso_presente": true,
      "respirando": true
    },
    {
      "hora": "17:30",
      "consciente": true,
      "glasgow": 15,
      "spo2": 95,
      "frequencia_cardiaca": 92,
      "temperatura": 37.3,
      "escala_dor": 4,
      "vomitos_por_hora": 1,
      "pulso_presente": true,
      "respirando": true
    }
  ]
}